configreader.py
configreader-0.0.6.dist-info/top_level.txt
configreader-0.0.6.dist-info/METADATA
configreader-0.0.6.dist-info/DESCRIPTION.rst
configreader-0.0.6.dist-info/metadata.json
configreader-0.0.6.dist-info/WHEEL
configreader-0.0.6.dist-info/RECORD
